{
  "$schema": "../../schema/class.schema.json",
  "id": "warlock",
  "name": "Bruxo",
  "source": {
    "book": "Livro do Jogador 2024",
    "language": "pt-BR",
    "chapter": 3,
    "chapterTitle": "Classes de Personagem",
    "pdfPath": "doc/livro-jogador.pdf",
    "pdfPages": [
      55,
      182
    ],
    "extractedAt": "2026-06-25T01:13:29.372Z"
  },
  "tagline": "Ocultista fortalecido com pactos sobrenaturais",
  "summary": "Conjure magias derivadas de conhecimento oculto.",
  "primaryAbility": "Carisma",
  "hitDie": "D8",
  "savingThrows": [
    "Sabedoria",
    "Carisma"
  ],
  "skillChoices": {
    "count": 2,
    "from": [
      "Arcanismo",
      "Enganação",
      "História",
      "Intimidação",
      "Investigação",
      "Natureza",
      "Religião"
    ]
  },
  "weaponProficiencies": [
    "Armas Simples"
  ],
  "armorTraining": {
    "light": true,
    "medium": false,
    "heavy": false,
    "shields": false
  },
  "startingEquipment": {
    "options": [
      {
        "label": "A",
        "items": [
          "Armadura de Couro",
          "Foice",
          "2 Adagas",
          "Foco Arcano (orbe)",
          "Livro (conhecimento oculto)",
          "Kit de Erudito",
          "15 PO"
        ]
      },
      {
        "label": "B",
        "items": [
          "100 PO"
        ]
      }
    ]
  },
  "spellcasting": {
    "type": "pact",
    "ability": "Carisma",
    "focus": "Foco Arcano",
    "ritual": false
  },
  "subclassUnlockLevel": 3,
  "subclassLabel": "Patrono",
  "subclasses": [
    "archfey",
    "celestial",
    "great-old-one",
    "fiend"
  ],
  "related": {
    "spells": [
      "Lista de Magias de Bruxo"
    ],
    "feats": [
      "Aumento no Valor de Atributo",
      "Dádiva Épica"
    ],
    "chapter": "Capítulo 5 — Talentos"
  },
  "features": [
    {
      "level": 1,
      "name": "Invocações Místicas",
      "description": "Você descobriu Invocações Místicas, fragmentos de\nconhecimento proibido que lhe conferem uma habilidade mágica permanente ou outros ensinamentos.\nVocê recebe uma invocação à sua escolha, como Pacto\ndo Tomo. As invocações são descritas na seção “Opções de Invocações Místicas” mais adiante na descrição\ndesta classe.\nPré-requisitos. Se uma invocação tiver um pré-requisito, você deve atendê-lo para aprender essa invocação.\nPor exemplo, se uma invocação exigir que você seja um\nBruxo de nível 5 ou superior, você pode selecionar a\ninvocação quando alcançar o nível 5 de Bruxo.\nSubstituindo e Recebendo outras Invocações. Ao\nalcançar um nível de Bruxo, você pode substituir uma\nde suas invocações por outra para a qual se qualifica.\nVocê não pode substituir uma invocação se ela for um\npré-requisito para outra invocação que você tenha.\nAo alcançar certos níveis de Bruxo, você adquire\nmais invocações à sua escolha, conforme mostrado na\ncoluna Invocações da tabela Características de Bruxo.\nVocê não pode escolher a mesma invocação mais de\numa vez, a menos que a descrição da invocação indique\no contrário."
    },
    {
      "level": 1,
      "name": "Magia de Pacto",
      "description": "Por meio de uma cerimônia oculta, você realizou um\npacto com uma entidade misteriosa para obter poderes\nmágicos. Essa voz nas sombras é enigmática, mas a dádiva concedida por ela é clara: a habilidade de conjurar\nmagias. Veja o capítulo 7 para as regras de conjuração.\nAs informações a seguir explicam como aplicar essas\nregras às magias de Bruxo, que estão listadas mais\nadiante na descrição da classe.\nTruques. Você conhece dois truques de Bruxo\nà sua escolha. Prestidigitação Arcana e Raio Místico\nsão recomendados. Ao alcançar um nível de Bruxo, \nvocê pode substituir um dos seus truques dessa\ncaracterística por outro truque de Bruxo à sua escolha.\nAo atingir os níveis 4 e 10 de Bruxo, você aprende\nmais um truque de Bruxo à sua escolha, conforme\ndetalhado na coluna Truques da tabela Características\nde Bruxo.\nEspaços de Magia. A tabela Características de Bruxo\nmostra quantos espaços de magia você tem para\nconjurar suas magias de Bruxo de 1º a 5º círculo. A\ntabela também mostra o círculo desses espaços, todos\ndo mesmo círculo. Você restaura todos os espaços\nde Magia de Pacto gastos ao completar um Descanso\nCurto ou Longo.\nPor exemplo, quando você é um Bruxo de nível 5,\nvocê tem dois espaços de magia de 3º círculo. Para\nconjurar a magia Raio de Bruxa de 1º círculo, você deve\ngastar um desses espaços e conjurá-la como uma magia\nde 3º círculo.\nMagias Preparadas de 1º Círculo ou Superior. Você\nprepara a lista de magias de 1º círculo ou superior\nque estão disponíveis para você conjurar com essa\ncaracterística. Para começar, escolha duas magias de\nBruxo de 1º círculo. Danação e Enfeitiçar Pessoa são\nrecomendadas.\nO número de magias em sua lista aumenta à medida\nque você alcança níveis de Bruxo, conforme mostrado\nna coluna Magias Preparadas da tabela Características\nde Bruxo. Quando esse número aumentar, escolha magias adicionais de Bruxo até que o número de magias\nem sua lista corresponda ao número da tabela. As magias escolhidas devem ser de um círculo não superior\nmostrado na coluna círculo do Espaço da tabela para o\nseu nível. Quando você atinge o nível 6, por exemplo,\nvocê aprende uma nova magia de Bruxo, que pode ser\nde 1º a 3º círculo.\nSe outra característica de Bruxo lhe concede magias\nsempre preparadas, elas não contam para o número de\nmagias que você pode preparar com essa característica,\nmas ainda são consideradas magias de Bruxo para você.\nMudando Suas Magias Preparadas. Sempre que você\nganha um nível de Bruxo, pode substituir uma magia\nda sua lista por outra magia de Bruxo de um nível\nelegível.\nAtributo de Conjuração. Carisma é o atributo de\nconjuração para suas magias de Bruxo.\nFoco de Conjuração. Você pode usar um Foco Arcano\ncomo um Foco de Conjuração para suas magias de\nBruxo."
    },
    {
      "level": 2,
      "name": "Astúcia Mágica",
      "description": "Ao final de um rito esotérico que você pode realizar\npor 1 minuto, você recupera os espaços de magia das\nMagias de Pacto gastos em um número igual à metade\nda sua quantidade máxima (arredondado para cima).\nVocê pode usar esta característica novamente após\ncompletar um Descanso Longo."
    },
    {
      "level": 3,
      "name": "Subclasse de Bruxo",
      "description": "Você adquire uma subclasse de Bruxo à sua escolha.\nAs subclasses Patrono Arquifada, Patrono Celestial,\nPatrono Grande Antigo e Patrono Ínfero estão detalhadas após a descrição desta classe. Uma subclasse é\numa especialidade que concede a você características\nem determinados níveis de Bruxo. Durante toda sua\njornada, você adquire cada uma das características de\nsua subclasse de seu nível de Bruxo ou menor."
    },
    {
      "level": 4,
      "name": "Aumento no Valor de Atributo",
      "description": "Você adquire o talento Aumento no Valor de Atributo\n(veja o capítulo 5) ou outro talento à sua escolha para\no qual atenda os pré-requisitos. Você adquire essa característica novamente nos níveis 8, 12 e 16 de Bruxo."
    },
    {
      "level": 9,
      "name": "Contatar Patrono",
      "description": "No passado, você entrava em contato com seu patrono\npor meio de intermediários. Agora, você pode se comunicar diretamente com ele. Você sempre tem a magia Contato Extraplanar preparada. Com esta característica, você\npode conjurar a magia sem gastar um espaço de magia\npara entrar em contato com seu patrono, e você é bem-sucedido automaticamente na salvaguarda da magia.\nVocê pode conjurar a magia com esta característica\nnovamente após completar um Descanso Longo."
    },
    {
      "level": 11,
      "name": "Arcana Mística",
      "description": "Seu patrono lhe concede um segredo mágico chamado\narcanum. Escolha uma magia de Bruxo de 6º círculo\ncom este arcanum.\nVocê pode conjurar sua magia arcanum uma vez sem\ngastar um espaço de magia, e novamente desta forma\napós completar um Descanso Longo.\nConforme mostrado na tabela Características de\nBruxo, você recebe outra magia de Bruxo à sua escolha\nque pode ser conjurada deste modo ao atingir os níveis\nde Bruxo 13 (magia de 7º círculo), 15 (magia de 8º círculo) e 17 (magia de 9º círculo). Você restaura todos os\nusos da sua Arcana Mística ao completar um Descanso\nLongo.\nAo alcançar um nível de Bruxo, você pode substituir\numa de suas magias de arcanum por outra magia de\nBruxo do mesmo círculo."
    },
    {
      "level": 19,
      "name": "Dádiva Épica",
      "description": "Você adquire o talento Dádiva Épica (veja o capítulo 5)\nou outro talento à sua escolha para o qual se qualifica.\nO talento Dádiva do Destino é recomendado."
    },
    {
      "level": 20,
      "name": "Mestre Místico",
      "description": "Ao usar sua característica Astúcia Mágica, você restaura todos os seus espaços de magia gastos das suas\nMagias de Pacto.\nOpções de Invocações Místicas\nAs opções de Invocações Místicas aparecem em ordem\nalfabética.\nArmadura de Sombras\nVocê pode conjurar Armadura Arcana em si sem gastar\num espaço de magia.\nExplosão Agonizante\nPré-requisitos: Bruxo Nível 2 ou superior, um Truque de\nBruxo que Cause Dano\nEscolha um dos seus truques conhecidos de Bruxo que\ncause dano. Você pode adicionar seu modificador de\nCarisma às jogadas de dano dessa magia.\nRepetível. Você pode adquirir esta invocação mais\nde uma vez, escolhendo um truque elegível diferente a\ncada vez.\nExplosão Repulsiva\nPré-requisitos: Bruxo Nível 2 ou superior, um Truque de\nBruxo que Cause Dano com uma Jogada de Ataque\nEscolha um dos seus truques conhecidos de Bruxo que\nexija uma jogada de ataque. Ao atingir uma criatura\nGrande ou menor com esse truque, você pode empurrá-la até 3 metros para longe de você.\nRepetível. Você pode adquirir esta invocação mais\nde uma vez, escolhendo um truque elegível diferente a\ncada vez.\nInvestimento do Mestre da Corrente\nPré-requisitos: Bruxo Nível 5 ou superior, Pacto da Corrente\nAo conjurar Convocar Familiar, você infunde o familiar\ninvocado com uma dose de seu poder místico, concedendo à criatura os seguintes benefícios.\nAéreo ou Aquático. O familiar obtém um Deslocamento de Voo ou um Deslocamento de Natação (à sua\nescolha) de 12 metros.\nAtaque Rápido. Como uma Ação Bônus, você pode\nordenar o familiar a executar a ação Atacar.\nCD para Evitar sua Magia. Se o familiar forçar uma\ncriatura a realizar uma salvaguarda, ela usa a CD para\nevitar sua magia.\nDano Necrótico ou Radiante. Sempre que o familiar\ncausar dano Contundente, Cortante ou Perfurante,\nvocê pode substituir o dano por Necrótico ou Radiante.\nResistência. Quando o familiar sofre dano, você pode\nexecutar uma Reação para conceder Resistência contra\nesse dano.\nLamento das Sepulturas\nPré-requisito: Bruxo Nível 7 ou superior\nVocê pode conjurar Falar com Mortos sem gastar um\nespaço de magia.\nLâmina Devoradora\nPré-requisito: Bruxo Nível 12 ou superior, Lâmina\nSedenta\nO Ataque Extra da sua invocação Lâmina Sedenta\nconcede dois ataques extras em vez de um.\nLâmina Sedenta\nPré-requisitos: Bruxo Nível 5 ou superior, Pacto da Lâmina\nVocê adquire a característica Ataque Extra apenas\npara sua arma de pacto e você pode atacar duas vezes\ncom ela, em vez de uma, quando executar a ação Atacar no seu turno.\n\nLança Mística\nPré-requisitos: Bruxo Nível 2 ou superior, um Truque de\nBruxo que Cause Dano\nEscolha um dos seus truques conhecidos de Bruxo que\ncause dano e tenha um alcance de 3 metros ou mais.\nAo conjurar essa magia, seu alcance aumenta em um\nnúmero de metros igual a 9 vezes o seu nível de Bruxo.\nRepetível. Você pode adquirir esta invocação mais\nde uma vez, escolhendo um truque elegível diferente a\ncada vez.\nLições dos Grandes Antigos\nPré-requisito: Bruxo Nível 2 ou superior\nVocê recebeu conhecimento de uma entidade antiga do\nmultiverso, permitindo que você obtenha um talento\nde Origem à sua escolha.\nRepetível. Você pode adquirir esta invocação mais de\numa vez, escolhendo um talento de Origem diferente\ncada vez.\nMáscara das Muitas Faces\nPré-requisito: Bruxo Nível 2 ou superior\nVocê pode conjurar Disfarçar-se sem gastar um espaço\nde magia.\nMente Mística\nVocê tem Vantagem em salvaguardas de Constituição\nque realiza para manter a Concentração.\nMestre das Infindáveis Formas\nPré-requisito: Bruxo Nível 5 ou superior\nVocê pode conjurar Alterar-se sem gastar um espaço de\nmagia.\nOlhar de Duas Mentes\nPré-requisito: Bruxo Nível 5 ou superior\nComo uma Ação Bônus, você pode tocar uma criatura\nvoluntária e perceber através de seus sentidos até o\nfinal do seu próximo turno. Enquanto a criatura estiver\nno mesmo plano de existência que você, você pode executar uma Ação Bônus nos turnos subsequentes para\nmanter essa conexão, estendendo a duração até o final\ndo seu próximo turno. A conexão encerra se você não\na mantiver deste modo.\nAo perceber através dos sentidos da outra criatura,\nvocê se beneficia de quaisquer sentidos especiais possuídos por ela e pode conjurar magias como se estivesse em seu espaço ou no espaço da outra criatura se\nvocês dois estiverem a até 18 metros um do outro.\nPacto da Corrente\nVocê aprende a magia Convocar Familiar e pode conjurá-la como uma ação Usar Magia sem gastar um espaço\nde magia.\nAo conjurar a magia, você escolhe uma das formas\nnormais para o seu familiar ou uma das seguintes formas especiais: Cobra Peçonhenta, Diabrete, Esfinge\nMaravilhosa, Esqueleto, Pseudodragão, Quasit,\nSlaad Girino, Sprite (veja o apêndice B para o bloco\nde estatísticas do familiar).\nAlém disso, ao executar ação Atacar, você pode\nrenunciar a um de seus próprios ataques para permitir\nque seu familiar realize um ataque próprio como uma\nReação dele.\nPacto da Lâmina\nComo uma Ação Bônus, você pode conjurar uma arma\nde pacto em sua mão — uma arma Corpo a Corpo\nSimples ou Marcial à sua escolha com a qual você se\nvincula — ou cria um vínculo com uma arma mágica\nque você toca; você não pode se vincular a uma arma\nmágica se outra pessoa estiver sintonizada ou outro\nBruxo tiver vínculo com ela. Até que o vínculo encerre,\nvocê tem proficiência com a arma e pode usá-la como\nFoco de Conjuração.\nAo atacar com a arma vinculada, você pode usar seu\nmodificador de Carisma para as jogadas de ataque e\ndano em vez de usar Força ou Destreza; e você pode\ncausar dano Necrótico, Psíquico ou Radiante ou o tipo\nde dano normal da arma.\nSeu vínculo com a arma encerra se você executar a\nAção Bônus desta característica novamente, se a arma\nestiver a mais de 1,5 metro de você por 1 minuto ou\nmais, ou se você morrer. Uma arma conjurada desaparece quando o vínculo encerra.\nPacto do Tomo\nAo costurar fios de sombra, você conjura um livro em\nsua mão ao final de um Descanso Curto ou Longo. Este\nLivro das Sombras (você determina a aparência dele)\ncontém magia mística que só você pode acessar, concedendo-lhe os benefícios abaixo. O livro desaparece se\nvocê conjurar outro livro com essa característica ou se\nvocê morrer.\nTruques e Rituais. Quando o livro surgir, escolha três\ntruques e duas magias de 1º círculo que tenham o marcador Ritual. As magias podem ser da lista de magias\nde qualquer classe e devem ser magias que você ainda\nnão tem preparadas. Enquanto o livro estiver com\nvocê, você tem as magias escolhidas preparadas e elas\nfuncionam como magias de Bruxo para você.\nFoco de Conjuração. Você pode usar o livro como um\nFoco de Conjuração.\nPasso Ascendente\nPré-requisito: Bruxo Nível 5 ou superior\nVocê pode conjurar Levitação em si sem gastar um\nespaço de magia.\nPresente das Profundezas\nPré-requisito: Bruxo Nível 5 ou superior\nVocê pode respirar debaixo d’água e obter um Deslocamento de Natação igual ao seu Deslocamento.\n\nVocê também pode conjurar Respirar na Água uma\nvez sem gastar um espaço de magia e novamente sempre que completar um Descanso Longo.\nPresente dos Protetores\nPré-requisitos: Bruxo Nível 9 ou superior, Pacto do Tomo\nUma nova página aparece em seu Livro das Sombras\nquando você o conjura. Com sua permissão, uma\ncriatura pode executar uma ação para escrever o nome\ndela nesta página, que pode conter um número de\nnomes igual ao seu modificador de Carisma (mínimo\nde um nome).\nQuando qualquer criatura cujo nome está na página\né reduzida a 0 Pontos de Vida, mas não morta imediatamente, a criatura magicamente tem 1 Ponto de Vida.\nUma vez que essa magia é acionada, nenhuma criatura pode se beneficiar dela até que você complete um\nDescanso Longo.\nComo uma ação Usar Magia, você pode apagar um\nnome na página tocando nele.\nPunição Mística\nPré-requisitos: Bruxo Nível 5 ou superior, Pacto da Lâmina\nUma vez por turno, ao atingir uma criatura com sua\narma de pacto, você pode gastar um espaço de Magia\nde Pacto para causar 1d8 pontos de dano Energético\nadicionais ao alvo, mais 1d8 por círculo do espaço de\nmagia, e pode impor ao alvo a condição Caído se ele for\nEnorme ou menor.\nSalto Sobrenatural\nPré-requisito: Bruxo Nível 2 ou superior\nVocê pode conjurar Salto em si sem gastar um espaço\nde magia.\nSorvedouro de Vida\nPré-requisitos: Bruxo Nível 9 ou superior, Pacto da Lâmina\nUma vez por turno, ao atingir uma criatura com sua\narma de pacto, você pode causar à criatura 1d6 pontos\nde dano Necrótico, Psíquico ou Radiante adicionais (à\nsua escolha) e você pode gastar um de seus Dados de\nPontos de Vida para jogá-lo e recuperar um número de\nPontos de Vida igual ao resultado mais seu modificador\nde Constituição (mínimo de 1 Ponto de Vida).\nUno com as Sombras\nPré-requisito: Bruxo Nível 5 ou superior\nEnquanto estiver em uma área de Meia-luz ou Escuridão, você pode conjurar Invisibilidade em si sem gastar\num espaço de magia.\nVigor Ínfero\nPré-requisito: Bruxo Nível 2 ou superior\nVocê pode conjurar Vitalidade Vazia em si sem gastar\num espaço de magia. Ao conjurar a magia com essa\ncaracterística, você não joga o dado para os Pontos\nde Vida Temporários, pois recebe automaticamente o\nnúmero máximo no dado.\nVisão da Bruxa\nPré-requisito: Bruxo Nível 15 ou superior\nVocê tem Visão Verdadeira com um alcance de 9 metros.\nVisão Diabólica\nPré-requisito: Bruxo Nível 2 ou superior\nVocê pode ver normalmente em Meia-luz e Escuridão\n— mágicas e não mágicas — a até 36 metros de você.\nVisões de Reinos Distantes\nPré-requisito: Bruxo Nível 9 ou superior\nVocê pode conjurar Olho Arcano sem gastar um espaço\nde magia.\nVisões Nebulosas\nPré-requisito: Bruxo Nível 2 ou superior\nVocê pode conjurar Imagem Silenciosa sem gastar um\nespaço de magia."
    }
  ],
  "progression": {
    "tableTitle": "Características de Bruxo",
    "columns": [
      "proficiencyBonus",
      "invocations",
      "cantrips",
      "preparedSpells",
      "pactSlots",
      "pactSlotLevel"
    ],
    "levels": [
      {
        "level": 1,
        "proficiencyBonus": 2,
        "invocations": 1,
        "cantrips": 2,
        "preparedSpells": 2,
        "pactSlots": 1,
        "pactSlotLevel": 1
      },
      {
        "level": 2,
        "proficiencyBonus": 2,
        "invocations": 3,
        "cantrips": 2,
        "preparedSpells": 3,
        "pactSlots": 2,
        "pactSlotLevel": 1
      },
      {
        "level": 3,
        "proficiencyBonus": 2,
        "invocations": 3,
        "cantrips": 2,
        "preparedSpells": 4,
        "pactSlots": 2,
        "pactSlotLevel": 2
      },
      {
        "level": 4,
        "proficiencyBonus": 2,
        "invocations": 3,
        "cantrips": 3,
        "preparedSpells": 5,
        "pactSlots": 2,
        "pactSlotLevel": 2
      },
      {
        "level": 5,
        "proficiencyBonus": 3,
        "invocations": 5,
        "cantrips": 3,
        "preparedSpells": 6,
        "pactSlots": 2,
        "pactSlotLevel": 3
      },
      {
        "level": 6,
        "proficiencyBonus": 3,
        "invocations": 5,
        "cantrips": 3,
        "preparedSpells": 7,
        "pactSlots": 2,
        "pactSlotLevel": 3
      },
      {
        "level": 7,
        "proficiencyBonus": 3,
        "invocations": 6,
        "cantrips": 3,
        "preparedSpells": 8,
        "pactSlots": 2,
        "pactSlotLevel": 4
      },
      {
        "level": 8,
        "proficiencyBonus": 3,
        "invocations": 6,
        "cantrips": 3,
        "preparedSpells": 9,
        "pactSlots": 2,
        "pactSlotLevel": 4
      },
      {
        "level": 9,
        "proficiencyBonus": 4,
        "invocations": 7,
        "cantrips": 3,
        "preparedSpells": 10,
        "pactSlots": 2,
        "pactSlotLevel": 5
      },
      {
        "level": 10,
        "proficiencyBonus": 4,
        "invocations": 7,
        "cantrips": 4,
        "preparedSpells": 10,
        "pactSlots": 2,
        "pactSlotLevel": 5
      },
      {
        "level": 11,
        "proficiencyBonus": 4,
        "invocations": 7,
        "cantrips": 4,
        "preparedSpells": 11,
        "pactSlots": 3,
        "pactSlotLevel": 5
      },
      {
        "level": 12,
        "proficiencyBonus": 4,
        "invocations": 8,
        "cantrips": 4,
        "preparedSpells": 11,
        "pactSlots": 3,
        "pactSlotLevel": 5
      },
      {
        "level": 13,
        "proficiencyBonus": 5,
        "invocations": 8,
        "cantrips": 4,
        "preparedSpells": 12,
        "pactSlots": 3,
        "pactSlotLevel": 5
      },
      {
        "level": 14,
        "proficiencyBonus": 5,
        "invocations": 8,
        "cantrips": 4,
        "preparedSpells": 12,
        "pactSlots": 3,
        "pactSlotLevel": 5
      },
      {
        "level": 15,
        "proficiencyBonus": 5,
        "invocations": 9,
        "cantrips": 4,
        "preparedSpells": 13,
        "pactSlots": 3,
        "pactSlotLevel": 5
      },
      {
        "level": 16,
        "proficiencyBonus": 5,
        "invocations": 9,
        "cantrips": 4,
        "preparedSpells": 13,
        "pactSlots": 3,
        "pactSlotLevel": 5
      },
      {
        "level": 17,
        "proficiencyBonus": 6,
        "invocations": 9,
        "cantrips": 4,
        "preparedSpells": 14,
        "pactSlots": 4,
        "pactSlotLevel": 5
      },
      {
        "level": 18,
        "proficiencyBonus": 6,
        "invocations": 10,
        "cantrips": 4,
        "preparedSpells": 14,
        "pactSlots": 4,
        "pactSlotLevel": 5
      },
      {
        "level": 19,
        "proficiencyBonus": 6,
        "invocations": 10,
        "cantrips": 4,
        "preparedSpells": 15,
        "pactSlots": 4,
        "pactSlotLevel": 5
      },
      {
        "level": 20,
        "proficiencyBonus": 6,
        "invocations": 10,
        "cantrips": 4,
        "preparedSpells": 15,
        "pactSlots": 4,
        "pactSlotLevel": 5
      }
    ]
  }
}
