{
  "$schema": "../../schema/ability-modifiers.schema.json",
  "id": "ability-modifiers",
  "source": {
    "book": "Livro do Jogador 2024",
    "language": "pt-BR",
    "chapter": 1,
    "pdfPath": "doc/livro-jogador.pdf",
    "pdfPages": [16, 16]
  },
  "abilities": [
    { "id": "forca", "name": "Força", "measures": "Potência física" },
    { "id": "destreza", "name": "Destreza", "measures": "Agilidade, reflexos e equilíbrio" },
    { "id": "constituicao", "name": "Constituição", "measures": "Saúde e resistência" },
    { "id": "inteligencia", "name": "Inteligência", "measures": "Raciocínio e memória" },
    { "id": "sabedoria", "name": "Sabedoria", "measures": "Perceptividade e fortaleza mental" },
    { "id": "carisma", "name": "Carisma", "measures": "Confiança, equilíbrio e charme" }
  ],
  "modifierTable": [
    { "scoreMin": 1, "scoreMax": 1, "modifier": -5 },
    { "scoreMin": 2, "scoreMax": 3, "modifier": -4 },
    { "scoreMin": 4, "scoreMax": 5, "modifier": -3 },
    { "scoreMin": 6, "scoreMax": 7, "modifier": -2 },
    { "scoreMin": 8, "scoreMax": 9, "modifier": -1 },
    { "scoreMin": 10, "scoreMax": 11, "modifier": 0 },
    { "scoreMin": 12, "scoreMax": 13, "modifier": 1 },
    { "scoreMin": 14, "scoreMax": 15, "modifier": 2 },
    { "scoreMin": 16, "scoreMax": 17, "modifier": 3 },
    { "scoreMin": 18, "scoreMax": 19, "modifier": 4 },
    { "scoreMin": 20, "scoreMax": 21, "modifier": 5 },
    { "scoreMin": 22, "scoreMax": 23, "modifier": 6 },
    { "scoreMin": 24, "scoreMax": 25, "modifier": 7 },
    { "scoreMin": 26, "scoreMax": 27, "modifier": 8 },
    { "scoreMin": 28, "scoreMax": 29, "modifier": 9 },
    { "scoreMin": 30, "scoreMax": 30, "modifier": 10 }
  ]
}
