{
  "$schema": "../../schema/spell.schema.json",
  "id": "campo-antimagia",
  "name": "Campo Antimagia",
  "level": 8,
  "levelLabel": "8º Círculo",
  "school": "Abjuração",
  "classes": [
    "Clérigo",
    "Mago"
  ],
  "castingTime": "Ação",
  "range": "Pessoal",
  "components": {
    "verbal": true,
    "somatic": true,
    "material": true,
    "materialDescription": "raspas de ferro",
    "text": "V, S, M (raspas de ferro)"
  },
  "duration": "Concentração, até 1 hora",
  "concentration": true,
  "ritual": false,
  "description": "A lendária bruxa Tasha usa sua magia, oCaldeirão Borbulhante de Tasha, para produzir uma poção mágica.\nUma aura de antimagia envolve você em uma Emanação de 3 metros. Ninguém pode conjurar magias,\nexecutar a ação Usar Magia ou criar outros efeitos mágicos dentro da aura, e esses efeitos não podem ter como alvo ou afetar qualquer coisa dentro dela. As propriedades mágicas dos itens mágicos não funcionam dentro da aura ou em qualquer coisa dentro dela.\nÁreas de efeito criadas por magias ou outros efeitos mágicos não podem se estender para dentro da aura, e ninguém pode se teleportar para dentro ou para fora dela ou usar viagens planares para lá. Os portais se fecham temporariamente enquanto estão na aura.\nMagias em andamento, exceto aquelas conjuradas por um Artefato ou por uma divindade, são suprimidas na área. Enquanto um efeito é suprimido, ele não funciona, mas o tempo que ele gasta suprimido conta para sua duração\nDissipar Magia não tem efeito sobre a aura, e as auras criadas por diferentes magias de Campo Antimagia não se anulam.",
  "source": {
    "book": "Livro do Jogador 2024",
    "language": "pt-BR",
    "chapter": 7,
    "chapterTitle": "Magias",
    "pdfPath": "doc/livro-jogador.pdf",
    "pdfPages": [
      241,
      349
    ],
    "extractedAt": "2026-06-25T01:53:01.507Z"
  }
}
